docs/__init__.py
docs/autogen.py
docs/utils.py
scripts/__init__.py
scripts/check_pre_release.py
scripts/validate_proposed_package_version.py
tests/__init__.py
tests/config.py
tests/mock_client.py
tests/test_client.py
tests/test_id.py
tests/test_operations.py
tests/test_result_conversions.py
tests/test_to_ISODate.py
tests/test_to_ISODate_Array.py
tests/test_utils.py
tests/test_version_proposals.py
tests/test_versioning.py
tests/testcases.py
tests/timer.py
tests/api/__init__.py
tests/api/test_canal_transit_entity.py
tests/api/test_cargo_event_entity.py
tests/api/test_cargo_movement.py
tests/api/test_corporate_entity.py
tests/api/test_geography_entity.py
tests/api/test_missing_keys.py
tests/api/test_product_entity.py
tests/api/test_vessel_entity.py
tests/endpoints/__init__.py
tests/endpoints/test_asset_tanks.py
tests/endpoints/test_attributes.py
tests/endpoints/test_attributes_real.py
tests/endpoints/test_availability_breakdown.py
tests/endpoints/test_availability_search.py
tests/endpoints/test_availability_timeseries.py
tests/endpoints/test_canal_transit_real.py
tests/endpoints/test_canal_transit_timeseries_real.py
tests/endpoints/test_cargo_movements_real.py
tests/endpoints/test_cargo_time_series.py
tests/endpoints/test_cargo_time_series_real.py
tests/endpoints/test_corporations_real.py
tests/endpoints/test_corporations_search_result.py
tests/endpoints/test_destination_breakdown.py
tests/endpoints/test_eia_forecasts_real.py
tests/endpoints/test_fixtures.py
tests/endpoints/test_freight_pricing_search.py
tests/endpoints/test_freight_pricing_timeseries.py
tests/endpoints/test_geographies_real.py
tests/endpoints/test_movement_status_breakdown.py
tests/endpoints/test_onshore_inventories_search.py
tests/endpoints/test_onshore_inventories_timeseries.py
tests/endpoints/test_origin_breakdown.py
tests/endpoints/test_parent_product_breakdown.py
tests/endpoints/test_product_breakdown.py
tests/endpoints/test_products.py
tests/endpoints/test_products_real.py
vortexasdk-1.0.14.dist-info/LICENSE.txt
vortexasdk-1.0.14.dist-info/METADATA
vortexasdk-1.0.14.dist-info/WHEEL
vortexasdk-1.0.14.dist-info/top_level.txt
vortexasdk-1.0.14.dist-info/RECORD
