Metadata-Version: 2.1
Name: vortexasdk
Version: 1.0.14
Summary: Vortexa SDK
Home-page: https://github.com/vortechsa/python-sdk
Author: Vortexa Developers
Author-email: developers@vortexa.com
License: Apache Software License 2.0
Platform: UNKNOWN
Classifier: Programming Language :: Python :: 3.9
Classifier: License :: OSI Approved :: Apache Software License
Classifier: Operating System :: OS Independent
Requires-Python: >=3.9
Requires-Dist: urllib3 (>=1.26)
Requires-Dist: flatten-dict (>=0.4.2)
Requires-Dist: pandas (>=2.0.0)
Requires-Dist: requests (>=2.31.0)
Requires-Dist: pydantic (<3.0.0,>=2.0.0)
Requires-Dist: tqdm (<5.0.0)
Provides-Extra: binder
Requires-Dist: jupyter (==1.0.0) ; extra == 'binder'
Requires-Dist: statsmodels (>=0.13.5) ; extra == 'binder'
Requires-Dist: matplotlib (>=3.5.3) ; extra == 'binder'
Provides-Extra: deploy
Requires-Dist: wheel (==0.37.1) ; extra == 'deploy'
Requires-Dist: twine (>=5.0.0) ; extra == 'deploy'
Provides-Extra: tests
Requires-Dist: flake8 (==3.7.9) ; extra == 'tests'
Requires-Dist: black (==23.1.0) ; extra == 'tests'
Requires-Dist: mkdocs (==1.2.4) ; extra == 'tests'
Requires-Dist: mypy (==1.9.0) ; extra == 'tests'
Requires-Dist: pre-commit (==1.20.0) ; extra == 'tests'
Requires-Dist: pytest (==8.1.1) ; extra == 'tests'
Requires-Dist: pydoc-markdown (==2.1.3) ; extra == 'tests'
Requires-Dist: pyyaml (==6.0.1) ; extra == 'tests'
Requires-Dist: six (==1.16.0) ; extra == 'tests'
Requires-Dist: tabulate (==0.9.0) ; extra == 'tests'
Requires-Dist: xlrd (==1.2.0) ; extra == 'tests'
Requires-Dist: openpyxl (==3.0.7) ; extra == 'tests'
Requires-Dist: types-requests (==2.28.9) ; extra == 'tests'
Requires-Dist: types-urllib3 (==1.26.23) ; extra == 'tests'
Requires-Dist: types-tabulate (==0.9.0) ; extra == 'tests'
Requires-Dist: types-python-dateutil (==2.8.19) ; extra == 'tests'
Requires-Dist: types-six (==1.16.21.20240311) ; extra == 'tests'
Requires-Dist: jupyter (==1.0.0) ; extra == 'tests'
Requires-Dist: statsmodels (==0.13.5) ; extra == 'tests'
Requires-Dist: matplotlib (>=3.5.3) ; extra == 'tests'
Requires-Dist: packaging (>=24.0) ; extra == 'tests'
